kson/__init__.py
kson/_marker.abi3.so
kson/_marker.c
kson/kson_api.h
kson/libkson.so
kson_lang-0.2.0.dist-info/METADATA
kson_lang-0.2.0.dist-info/WHEEL
kson_lang-0.2.0.dist-info/top_level.txt
kson_lang-0.2.0.dist-info/RECORD
kson_lang-0.2.0.dist-info/licenses/LICENSE
